{
  "name": "wolfram",
  "rules": {
    "source_file": {
      "type": "REPEAT",
      "content": {
        "type": "SYMBOL",
        "name": "_expression"
      }
    },
    "_expression": {
      "type": "CHOICE",
      "members": [
        {
          "type": "SYMBOL",
          "name": "_leaf"
        },
        {
          "type": "SYMBOL",
          "name": "prefix"
        },
        {
          "type": "SYMBOL",
          "name": "postfix"
        },
        {
          "type": "SYMBOL",
          "name": "binary"
        },
        {
          "type": "SYMBOL",
          "name": "infix"
        },
        {
          "type": "SYMBOL",
          "name": "call"
        },
        {
          "type": "SYMBOL",
          "name": "group"
        }
      ]
    },
    "_leaf": {
      "type": "CHOICE",
      "members": [
        {
          "type": "SYMBOL",
          "name": "symbol"
        },
        {
          "type": "SYMBOL",
          "name": "integer"
        },
        {
          "type": "SYMBOL",
          "name": "real"
        },
        {
          "type": "SYMBOL",
          "name": "string"
        }
      ]
    },
    "symbol": {
      "type": "PATTERN",
      "value": "[a-zA-Z]+"
    },
    "integer": {
      "type": "PATTERN",
      "value": "[0-9]+"
    },
    "real": {
      "type": "PATTERN",
      "value": "[0-9]+\\.[0-9]"
    },
    "string": {
      "type": "PATTERN",
      "value": "\\\".*\\\""
    },
    "prefix": {
      "type": "CHOICE",
      "members": [
        {
          "type": "PREC",
          "value": 64,
          "content": {
            "type": "SEQ",
            "members": [
              {
                "type": "STRING",
                "value": "!"
              },
              {
                "type": "SYMBOL",
                "name": "_expression"
              }
            ]
          }
        },
        {
          "type": "PREC",
          "value": 64,
          "content": {
            "type": "SEQ",
            "members": [
              {
                "type": "STRING",
                "value": "!!"
              },
              {
                "type": "SYMBOL",
                "name": "_expression"
              }
            ]
          }
        },
        {
          "type": "PREC",
          "value": 124,
          "content": {
            "type": "SEQ",
            "members": [
              {
                "type": "STRING",
                "value": "-"
              },
              {
                "type": "SYMBOL",
                "name": "_expression"
              }
            ]
          }
        },
        {
          "type": "PREC",
          "value": 124,
          "content": {
            "type": "SEQ",
            "members": [
              {
                "type": "STRING",
                "value": "+"
              },
              {
                "type": "SYMBOL",
                "name": "_expression"
              }
            ]
          }
        },
        {
          "type": "PREC",
          "value": 172,
          "content": {
            "type": "SEQ",
            "members": [
              {
                "type": "STRING",
                "value": "++"
              },
              {
                "type": "SYMBOL",
                "name": "_expression"
              }
            ]
          }
        },
        {
          "type": "PREC",
          "value": 172,
          "content": {
            "type": "SEQ",
            "members": [
              {
                "type": "STRING",
                "value": "--"
              },
              {
                "type": "SYMBOL",
                "name": "_expression"
              }
            ]
          }
        }
      ]
    },
    "postfix": {
      "type": "CHOICE",
      "members": [
        {
          "type": "PREC",
          "value": 24,
          "content": {
            "type": "SEQ",
            "members": [
              {
                "type": "SYMBOL",
                "name": "_expression"
              },
              {
                "type": "STRING",
                "value": "&"
              }
            ]
          }
        },
        {
          "type": "PREC",
          "value": 44,
          "content": {
            "type": "SEQ",
            "members": [
              {
                "type": "SYMBOL",
                "name": "_expression"
              },
              {
                "type": "STRING",
                "value": ".."
              }
            ]
          }
        },
        {
          "type": "PREC",
          "value": 44,
          "content": {
            "type": "SEQ",
            "members": [
              {
                "type": "SYMBOL",
                "name": "_expression"
              },
              {
                "type": "STRING",
                "value": "..."
              }
            ]
          }
        },
        {
          "type": "PREC",
          "value": 154,
          "content": {
            "type": "SEQ",
            "members": [
              {
                "type": "SYMBOL",
                "name": "_expression"
              },
              {
                "type": "STRING",
                "value": "'"
              }
            ]
          }
        },
        {
          "type": "PREC",
          "value": 158,
          "content": {
            "type": "SEQ",
            "members": [
              {
                "type": "SYMBOL",
                "name": "_expression"
              },
              {
                "type": "STRING",
                "value": "!"
              }
            ]
          }
        },
        {
          "type": "PREC",
          "value": 158,
          "content": {
            "type": "SEQ",
            "members": [
              {
                "type": "SYMBOL",
                "name": "_expression"
              },
              {
                "type": "STRING",
                "value": "!!"
              }
            ]
          }
        },
        {
          "type": "PREC",
          "value": 174,
          "content": {
            "type": "SEQ",
            "members": [
              {
                "type": "SYMBOL",
                "name": "_expression"
              },
              {
                "type": "STRING",
                "value": "--"
              }
            ]
          }
        },
        {
          "type": "PREC",
          "value": 174,
          "content": {
            "type": "SEQ",
            "members": [
              {
                "type": "SYMBOL",
                "name": "_expression"
              },
              {
                "type": "STRING",
                "value": "++"
              }
            ]
          }
        }
      ]
    },
    "binary": {
      "type": "CHOICE",
      "members": [
        {
          "type": "PREC_LEFT",
          "value": 9,
          "content": {
            "type": "SEQ",
            "members": [
              {
                "type": "SYMBOL",
                "name": "_expression"
              },
              {
                "type": "STRING",
                "value": "="
              },
              {
                "type": "SYMBOL",
                "name": "_expression"
              }
            ]
          }
        },
        {
          "type": "PREC_LEFT",
          "value": 9,
          "content": {
            "type": "SEQ",
            "members": [
              {
                "type": "SYMBOL",
                "name": "_expression"
              },
              {
                "type": "STRING",
                "value": ":="
              },
              {
                "type": "SYMBOL",
                "name": "_expression"
              }
            ]
          }
        },
        {
          "type": "PREC_LEFT",
          "value": 9,
          "content": {
            "type": "SEQ",
            "members": [
              {
                "type": "SYMBOL",
                "name": "_expression"
              },
              {
                "type": "STRING",
                "value": "^="
              },
              {
                "type": "SYMBOL",
                "name": "_expression"
              }
            ]
          }
        },
        {
          "type": "PREC_LEFT",
          "value": 9,
          "content": {
            "type": "SEQ",
            "members": [
              {
                "type": "SYMBOL",
                "name": "_expression"
              },
              {
                "type": "STRING",
                "value": "^:="
              },
              {
                "type": "SYMBOL",
                "name": "_expression"
              }
            ]
          }
        },
        {
          "type": "PREC_LEFT",
          "value": 9,
          "content": {
            "type": "SEQ",
            "members": [
              {
                "type": "SYMBOL",
                "name": "_expression"
              },
              {
                "type": "STRING",
                "value": "|->"
              },
              {
                "type": "SYMBOL",
                "name": "_expression"
              }
            ]
          }
        },
        {
          "type": "PREC_LEFT",
          "value": 18,
          "content": {
            "type": "SEQ",
            "members": [
              {
                "type": "SYMBOL",
                "name": "_expression"
              },
              {
                "type": "STRING",
                "value": "//"
              },
              {
                "type": "SYMBOL",
                "name": "_expression"
              }
            ]
          }
        },
        {
          "type": "PREC_RIGHT",
          "value": 21,
          "content": {
            "type": "SEQ",
            "members": [
              {
                "type": "SYMBOL",
                "name": "_expression"
              },
              {
                "type": "STRING",
                "value": "//="
              },
              {
                "type": "SYMBOL",
                "name": "_expression"
              }
            ]
          }
        },
        {
          "type": "PREC_RIGHT",
          "value": 27,
          "content": {
            "type": "SEQ",
            "members": [
              {
                "type": "SYMBOL",
                "name": "_expression"
              },
              {
                "type": "STRING",
                "value": "+="
              },
              {
                "type": "SYMBOL",
                "name": "_expression"
              }
            ]
          }
        },
        {
          "type": "PREC_RIGHT",
          "value": 27,
          "content": {
            "type": "SEQ",
            "members": [
              {
                "type": "SYMBOL",
                "name": "_expression"
              },
              {
                "type": "STRING",
                "value": "-="
              },
              {
                "type": "SYMBOL",
                "name": "_expression"
              }
            ]
          }
        },
        {
          "type": "PREC_RIGHT",
          "value": 27,
          "content": {
            "type": "SEQ",
            "members": [
              {
                "type": "SYMBOL",
                "name": "_expression"
              },
              {
                "type": "STRING",
                "value": "*="
              },
              {
                "type": "SYMBOL",
                "name": "_expression"
              }
            ]
          }
        },
        {
          "type": "PREC_RIGHT",
          "value": 27,
          "content": {
            "type": "SEQ",
            "members": [
              {
                "type": "SYMBOL",
                "name": "_expression"
              },
              {
                "type": "STRING",
                "value": "/="
              },
              {
                "type": "SYMBOL",
                "name": "_expression"
              }
            ]
          }
        },
        {
          "type": "PREC_LEFT",
          "value": 28,
          "content": {
            "type": "SEQ",
            "members": [
              {
                "type": "SYMBOL",
                "name": "_expression"
              },
              {
                "type": "STRING",
                "value": "/."
              },
              {
                "type": "SYMBOL",
                "name": "_expression"
              }
            ]
          }
        },
        {
          "type": "PREC_LEFT",
          "value": 28,
          "content": {
            "type": "SEQ",
            "members": [
              {
                "type": "SYMBOL",
                "name": "_expression"
              },
              {
                "type": "STRING",
                "value": "//."
              },
              {
                "type": "SYMBOL",
                "name": "_expression"
              }
            ]
          }
        },
        {
          "type": "PREC_RIGHT",
          "value": 31,
          "content": {
            "type": "SEQ",
            "members": [
              {
                "type": "SYMBOL",
                "name": "_expression"
              },
              {
                "type": "STRING",
                "value": "->"
              },
              {
                "type": "SYMBOL",
                "name": "_expression"
              }
            ]
          }
        },
        {
          "type": "PREC_RIGHT",
          "value": 31,
          "content": {
            "type": "SEQ",
            "members": [
              {
                "type": "SYMBOL",
                "name": "_expression"
              },
              {
                "type": "STRING",
                "value": ":>"
              },
              {
                "type": "SYMBOL",
                "name": "_expression"
              }
            ]
          }
        },
        {
          "type": "PREC_RIGHT",
          "value": 33,
          "content": {
            "type": "SEQ",
            "members": [
              {
                "type": "SYMBOL",
                "name": "_expression"
              },
              {
                "type": "STRING",
                "value": "<->"
              },
              {
                "type": "SYMBOL",
                "name": "_expression"
              }
            ]
          }
        },
        {
          "type": "PREC_LEFT",
          "value": 34,
          "content": {
            "type": "SEQ",
            "members": [
              {
                "type": "SYMBOL",
                "name": "_expression"
              },
              {
                "type": "STRING",
                "value": "/;"
              },
              {
                "type": "SYMBOL",
                "name": "_expression"
              }
            ]
          }
        },
        {
          "type": "PREC_LEFT",
          "value": 122,
          "content": {
            "type": "SEQ",
            "members": [
              {
                "type": "SYMBOL",
                "name": "_expression"
              },
              {
                "type": "STRING",
                "value": "/"
              },
              {
                "type": "SYMBOL",
                "name": "_expression"
              }
            ]
          }
        },
        {
          "type": "PREC_RIGHT",
          "value": 151,
          "content": {
            "type": "SEQ",
            "members": [
              {
                "type": "SYMBOL",
                "name": "_expression"
              },
              {
                "type": "STRING",
                "value": "^"
              },
              {
                "type": "SYMBOL",
                "name": "_expression"
              }
            ]
          }
        },
        {
          "type": "PREC_LEFT",
          "value": 161,
          "content": {
            "type": "SEQ",
            "members": [
              {
                "type": "SYMBOL",
                "name": "_expression"
              },
              {
                "type": "STRING",
                "value": "/@"
              },
              {
                "type": "SYMBOL",
                "name": "_expression"
              }
            ]
          }
        },
        {
          "type": "PREC_RIGHT",
          "value": 161,
          "content": {
            "type": "SEQ",
            "members": [
              {
                "type": "SYMBOL",
                "name": "_expression"
              },
              {
                "type": "STRING",
                "value": "@@"
              },
              {
                "type": "SYMBOL",
                "name": "_expression"
              }
            ]
          }
        },
        {
          "type": "PREC_LEFT",
          "value": 161,
          "content": {
            "type": "SEQ",
            "members": [
              {
                "type": "SYMBOL",
                "name": "_expression"
              },
              {
                "type": "STRING",
                "value": "//@"
              },
              {
                "type": "SYMBOL",
                "name": "_expression"
              }
            ]
          }
        },
        {
          "type": "PREC_LEFT",
          "value": 161,
          "content": {
            "type": "SEQ",
            "members": [
              {
                "type": "SYMBOL",
                "name": "_expression"
              },
              {
                "type": "STRING",
                "value": "@@@"
              },
              {
                "type": "SYMBOL",
                "name": "_expression"
              }
            ]
          }
        },
        {
          "type": "PREC_RIGHT",
          "value": 165,
          "content": {
            "type": "SEQ",
            "members": [
              {
                "type": "SYMBOL",
                "name": "_expression"
              },
              {
                "type": "STRING",
                "value": "@"
              },
              {
                "type": "SYMBOL",
                "name": "_expression"
              }
            ]
          }
        },
        {
          "type": "PREC_LEFT",
          "value": 178,
          "content": {
            "type": "SEQ",
            "members": [
              {
                "type": "SYMBOL",
                "name": "_expression"
              },
              {
                "type": "STRING",
                "value": "?"
              },
              {
                "type": "SYMBOL",
                "name": "_expression"
              }
            ]
          }
        }
      ]
    },
    "infix": {
      "type": "CHOICE",
      "members": [
        {
          "type": "PREC_LEFT",
          "value": 2,
          "content": {
            "type": "SEQ",
            "members": [
              {
                "type": "SYMBOL",
                "name": "_expression"
              },
              {
                "type": "STRING",
                "value": ","
              },
              {
                "type": "SYMBOL",
                "name": "_expression"
              }
            ]
          }
        },
        {
          "type": "PREC_LEFT",
          "value": 4,
          "content": {
            "type": "SEQ",
            "members": [
              {
                "type": "SYMBOL",
                "name": "_expression"
              },
              {
                "type": "STRING",
                "value": ";"
              },
              {
                "type": "SYMBOL",
                "name": "_expression"
              }
            ]
          }
        },
        {
          "type": "PREC_LEFT",
          "value": 36,
          "content": {
            "type": "SEQ",
            "members": [
              {
                "type": "SYMBOL",
                "name": "_expression"
              },
              {
                "type": "STRING",
                "value": "~~"
              },
              {
                "type": "SYMBOL",
                "name": "_expression"
              }
            ]
          }
        },
        {
          "type": "PREC_LEFT",
          "value": 42,
          "content": {
            "type": "SEQ",
            "members": [
              {
                "type": "SYMBOL",
                "name": "_expression"
              },
              {
                "type": "STRING",
                "value": "|"
              },
              {
                "type": "SYMBOL",
                "name": "_expression"
              }
            ]
          }
        },
        {
          "type": "PREC_LEFT",
          "value": 58,
          "content": {
            "type": "SEQ",
            "members": [
              {
                "type": "SYMBOL",
                "name": "_expression"
              },
              {
                "type": "STRING",
                "value": "||"
              },
              {
                "type": "SYMBOL",
                "name": "_expression"
              }
            ]
          }
        },
        {
          "type": "PREC_LEFT",
          "value": 62,
          "content": {
            "type": "SEQ",
            "members": [
              {
                "type": "SYMBOL",
                "name": "_expression"
              },
              {
                "type": "STRING",
                "value": "&&"
              },
              {
                "type": "SYMBOL",
                "name": "_expression"
              }
            ]
          }
        },
        {
          "type": "PREC_LEFT",
          "value": 70,
          "content": {
            "type": "SEQ",
            "members": [
              {
                "type": "SYMBOL",
                "name": "_expression"
              },
              {
                "type": "STRING",
                "value": "==="
              },
              {
                "type": "SYMBOL",
                "name": "_expression"
              }
            ]
          }
        },
        {
          "type": "PREC_LEFT",
          "value": 70,
          "content": {
            "type": "SEQ",
            "members": [
              {
                "type": "SYMBOL",
                "name": "_expression"
              },
              {
                "type": "STRING",
                "value": "=!="
              },
              {
                "type": "SYMBOL",
                "name": "_expression"
              }
            ]
          }
        },
        {
          "type": "PREC_LEFT",
          "value": 76,
          "content": {
            "type": "SEQ",
            "members": [
              {
                "type": "SYMBOL",
                "name": "_expression"
              },
              {
                "type": "STRING",
                "value": "=="
              },
              {
                "type": "SYMBOL",
                "name": "_expression"
              }
            ]
          }
        },
        {
          "type": "PREC_LEFT",
          "value": 76,
          "content": {
            "type": "SEQ",
            "members": [
              {
                "type": "SYMBOL",
                "name": "_expression"
              },
              {
                "type": "STRING",
                "value": "!="
              },
              {
                "type": "SYMBOL",
                "name": "_expression"
              }
            ]
          }
        },
        {
          "type": "PREC_LEFT",
          "value": 76,
          "content": {
            "type": "SEQ",
            "members": [
              {
                "type": "SYMBOL",
                "name": "_expression"
              },
              {
                "type": "STRING",
                "value": "<"
              },
              {
                "type": "SYMBOL",
                "name": "_expression"
              }
            ]
          }
        },
        {
          "type": "PREC_LEFT",
          "value": 76,
          "content": {
            "type": "SEQ",
            "members": [
              {
                "type": "SYMBOL",
                "name": "_expression"
              },
              {
                "type": "STRING",
                "value": "<="
              },
              {
                "type": "SYMBOL",
                "name": "_expression"
              }
            ]
          }
        },
        {
          "type": "PREC_LEFT",
          "value": 76,
          "content": {
            "type": "SEQ",
            "members": [
              {
                "type": "SYMBOL",
                "name": "_expression"
              },
              {
                "type": "STRING",
                "value": ">"
              },
              {
                "type": "SYMBOL",
                "name": "_expression"
              }
            ]
          }
        },
        {
          "type": "PREC_LEFT",
          "value": 76,
          "content": {
            "type": "SEQ",
            "members": [
              {
                "type": "SYMBOL",
                "name": "_expression"
              },
              {
                "type": "STRING",
                "value": ">="
              },
              {
                "type": "SYMBOL",
                "name": "_expression"
              }
            ]
          }
        },
        {
          "type": "PREC_LEFT",
          "value": 86,
          "content": {
            "type": "SEQ",
            "members": [
              {
                "type": "SYMBOL",
                "name": "_expression"
              },
              {
                "type": "STRING",
                "value": "+"
              },
              {
                "type": "SYMBOL",
                "name": "_expression"
              }
            ]
          }
        },
        {
          "type": "PREC_LEFT",
          "value": 86,
          "content": {
            "type": "SEQ",
            "members": [
              {
                "type": "SYMBOL",
                "name": "_expression"
              },
              {
                "type": "STRING",
                "value": "-"
              },
              {
                "type": "SYMBOL",
                "name": "_expression"
              }
            ]
          }
        },
        {
          "type": "PREC_LEFT",
          "value": 108,
          "content": {
            "type": "SEQ",
            "members": [
              {
                "type": "SYMBOL",
                "name": "_expression"
              },
              {
                "type": "STRING",
                "value": "*"
              },
              {
                "type": "SYMBOL",
                "name": "_expression"
              }
            ]
          }
        },
        {
          "type": "PREC_LEFT",
          "value": 126,
          "content": {
            "type": "SEQ",
            "members": [
              {
                "type": "SYMBOL",
                "name": "_expression"
              },
              {
                "type": "STRING",
                "value": "."
              },
              {
                "type": "SYMBOL",
                "name": "_expression"
              }
            ]
          }
        },
        {
          "type": "PREC_LEFT",
          "value": 132,
          "content": {
            "type": "SEQ",
            "members": [
              {
                "type": "SYMBOL",
                "name": "_expression"
              },
              {
                "type": "STRING",
                "value": "**"
              },
              {
                "type": "SYMBOL",
                "name": "_expression"
              }
            ]
          }
        },
        {
          "type": "PREC_LEFT",
          "value": 152,
          "content": {
            "type": "SEQ",
            "members": [
              {
                "type": "SYMBOL",
                "name": "_expression"
              },
              {
                "type": "STRING",
                "value": "<>"
              },
              {
                "type": "SYMBOL",
                "name": "_expression"
              }
            ]
          }
        },
        {
          "type": "PREC_LEFT",
          "value": 168,
          "content": {
            "type": "SEQ",
            "members": [
              {
                "type": "SYMBOL",
                "name": "_expression"
              },
              {
                "type": "STRING",
                "value": "/*"
              },
              {
                "type": "SYMBOL",
                "name": "_expression"
              }
            ]
          }
        },
        {
          "type": "PREC_LEFT",
          "value": 170,
          "content": {
            "type": "SEQ",
            "members": [
              {
                "type": "SYMBOL",
                "name": "_expression"
              },
              {
                "type": "STRING",
                "value": "@*"
              },
              {
                "type": "SYMBOL",
                "name": "_expression"
              }
            ]
          }
        }
      ]
    },
    "call": {
      "type": "PREC",
      "value": 176,
      "content": {
        "type": "SEQ",
        "members": [
          {
            "type": "SYMBOL",
            "name": "_expression"
          },
          {
            "type": "STRING",
            "value": "["
          },
          {
            "type": "SYMBOL",
            "name": "_expression"
          },
          {
            "type": "STRING",
            "value": "]"
          }
        ]
      }
    },
    "group": {
      "type": "CHOICE",
      "members": [
        {
          "type": "SEQ",
          "members": [
            {
              "type": "STRING",
              "value": "{"
            },
            {
              "type": "SYMBOL",
              "name": "_expression"
            },
            {
              "type": "STRING",
              "value": "}"
            }
          ]
        },
        {
          "type": "SEQ",
          "members": [
            {
              "type": "STRING",
              "value": "("
            },
            {
              "type": "SYMBOL",
              "name": "_expression"
            },
            {
              "type": "STRING",
              "value": ")"
            }
          ]
        },
        {
          "type": "SEQ",
          "members": [
            {
              "type": "STRING",
              "value": "["
            },
            {
              "type": "SYMBOL",
              "name": "_expression"
            },
            {
              "type": "STRING",
              "value": "]"
            }
          ]
        },
        {
          "type": "SEQ",
          "members": [
            {
              "type": "STRING",
              "value": "<|"
            },
            {
              "type": "SYMBOL",
              "name": "_expression"
            },
            {
              "type": "STRING",
              "value": "|>"
            }
          ]
        }
      ]
    }
  },
  "extras": [
    {
      "type": "SYMBOL",
      "name": "comment"
    },
    {
      "type": "PATTERN",
      "value": "\\s"
    }
  ],
  "conflicts": [],
  "precedences": [],
  "externals": [
    {
      "type": "SYMBOL",
      "name": "comment"
    }
  ],
  "inline": [],
  "supertypes": []
}

